sipg/__init__.py
sipg/cli.py
sipg/config.py
sipg/core.py
sipg-2.1.1.dist-info/licenses/LICENSE
tests/__init__.py
tests/test_config.py
sipg-2.1.1.dist-info/METADATA
sipg-2.1.1.dist-info/WHEEL
sipg-2.1.1.dist-info/entry_points.txt
sipg-2.1.1.dist-info/top_level.txt
sipg-2.1.1.dist-info/RECORD
