Metadata-Version: 2.4
Name: sipg
Version: 2.1.1
Summary: A professional command-line tool for searching IP addresses using Shodan API
Home-page: https://github.com/emptymahbob/sipg
Author: Mahbob Alam
Author-email: Mahbob Alam <emptymahbob@gmail.com>
Maintainer-email: Mahbob Alam <emptymahbob@gmail.com>
License-Expression: MIT
Project-URL: Homepage, https://github.com/emptymahbob/sipg
Project-URL: Documentation, https://github.com/emptymahbob/sipg#readme
Project-URL: Repository, https://github.com/emptymahbob/sipg
Project-URL: Bug Tracker, https://github.com/emptymahbob/sipg/issues
Keywords: shodan,ip,grabber,security,reconnaissance,network,api
Classifier: Development Status :: 5 - Production/Stable
Classifier: Intended Audience :: Information Technology
Classifier: Operating System :: OS Independent
Classifier: Programming Language :: Python :: 3
Classifier: Programming Language :: Python :: 3.7
Classifier: Programming Language :: Python :: 3.8
Classifier: Programming Language :: Python :: 3.9
Classifier: Programming Language :: Python :: 3.10
Classifier: Programming Language :: Python :: 3.11
Classifier: Programming Language :: Python :: 3.12
Classifier: Topic :: Internet :: WWW/HTTP :: Indexing/Search
Classifier: Topic :: Security
Classifier: Topic :: System :: Networking :: Monitoring
Classifier: Topic :: Utilities
Requires-Python: >=3.7
License-File: LICENSE
Requires-Dist: colorama>=0.4.4
Requires-Dist: requests>=2.26.0
Requires-Dist: click>=8.0.0
Requires-Dist: rich>=12.0.0
Provides-Extra: dev
Requires-Dist: pytest>=7.0.0; extra == "dev"
Requires-Dist: pytest-cov>=4.0.0; extra == "dev"
Requires-Dist: black>=22.0.0; extra == "dev"
Requires-Dist: flake8>=5.0.0; extra == "dev"
Requires-Dist: mypy>=1.0.0; extra == "dev"
Requires-Dist: pre-commit>=2.20.0; extra == "dev"
Dynamic: author
Dynamic: home-page
Dynamic: license-file
Dynamic: requires-python
